{
  "dashboard": {
    "style": "dark",
    "editable": true,
    "graphTooltip": 0,
    "schemaVersion": 36,
    "templating": {
      "list": [
        {
          "name": "service",
          "type": "constant",
          "current": {
            "value": "payment-api",
            "text": "payment-api"
          },
          "hide": 2,
          "query": "payment-api"
        }
      ]
    },
    "annotations": {},
    "uid": "payment-api-overview",
    "title": "payment-api - Service Dashboard",
    "description": "Auto-generated dashboard for payment-api service",
    "tags": [
      "platform",
      "standard",
      "api"
    ],
    "timezone": "browser",
    "time": {
      "from": "now-6h",
      "to": "now"
    },
    "fiscalYearStartMonth": 0,
    "panels": [
      {
        "type": "row",
        "collapsed": false,
        "id": 0,
        "panels": [],
        "title": "SLO Metrics",
        "gridPos": {
          "h": 1,
          "w": 24,
          "x": 0,
          "y": 0
        }
      },
      {
        "type": "timeseries",
        "transparent": false,
        "transformations": [],
        "options": null,
        "fieldConfig": {
          "defaults": {},
          "overrides": []
        },
        "targets": [
          {
            "expr": "sum(rate(http_requests_total{service=\"$service\"}[5m]))",
            "refId": "A"
          }
        ],
        "title": "availability",
        "description": "Target: 99.9%",
        "gridPos": {
          "h": 9,
          "w": 12,
          "x": 0,
          "y": 1
        },
        "repeatDirection": "h"
      },
      {
        "type": "row",
        "collapsed": false,
        "id": 0,
        "panels": [],
        "title": "Service Health",
        "gridPos": {
          "h": 1,
          "w": 24,
          "x": 0,
          "y": 10
        }
      },
      {
        "type": "timeseries",
        "transparent": false,
        "transformations": [],
        "options": null,
        "fieldConfig": {
          "defaults": {},
          "overrides": []
        },
        "targets": [
          {
            "expr": "sum(rate(http_requests_total{service=\"$service\"}[5m]))",
            "refId": "A",
            "legendFormat": "{{http}}"
          }
        ],
        "title": "Request Rate",
        "description": "Total requests per second",
        "gridPos": {
          "h": 9,
          "w": 12,
          "x": 0,
          "y": 11
        },
        "repeatDirection": "h"
      },
      {
        "type": "timeseries",
        "transparent": false,
        "transformations": [],
        "options": null,
        "fieldConfig": {
          "defaults": {},
          "overrides": []
        },
        "targets": [
          {
            "expr": "sum(rate(http_requests_total{service=\"$service\",status=~\"5..\"}[5m])) / sum(rate(http_requests_total{service=\"$service\"}[5m])) * 100",
            "refId": "A",
            "legendFormat": "error %"
          }
        ],
        "title": "Error Rate",
        "description": "Percentage of requests returning 5xx errors",
        "gridPos": {
          "h": 9,
          "w": 12,
          "x": 12,
          "y": 11
        },
        "repeatDirection": "h"
      },
      {
        "type": "timeseries",
        "transparent": false,
        "transformations": [],
        "options": null,
        "fieldConfig": {
          "defaults": {},
          "overrides": []
        },
        "targets": [
          {
            "expr": "histogram_quantile(0.95, sum by (le) (rate(http_request_duration_seconds_bucket{service=\"$service\"}[5m])))",
            "refId": "A",
            "legendFormat": "{{http}}"
          }
        ],
        "title": "Request Latency (p95)",
        "description": "95th percentile request duration",
        "gridPos": {
          "h": 9,
          "w": 12,
          "x": 0,
          "y": 20
        },
        "repeatDirection": "h"
      },
      {
        "type": "row",
        "collapsed": false,
        "id": 0,
        "panels": [],
        "title": "Dependencies",
        "gridPos": {
          "h": 1,
          "w": 24,
          "x": 0,
          "y": 29
        }
      },
      {
        "type": "timeseries",
        "transparent": false,
        "transformations": [],
        "options": null,
        "fieldConfig": {
          "defaults": {},
          "overrides": []
        },
        "targets": [
          {
            "expr": "pg_stat_database_numbackends{service=\"$service\"}",
            "refId": "A",
            "legendFormat": "{{datname}} connections"
          },
          {
            "expr": "pg_settings_max_connections{service=\"$service\"}",
            "refId": "B",
            "legendFormat": "Max connections"
          }
        ],
        "title": "PostgreSQL Connections",
        "description": "Active database connections vs max connections limit",
        "gridPos": {
          "h": 9,
          "w": 12,
          "x": 0,
          "y": 30
        },
        "repeatDirection": "h"
      },
      {
        "type": "timeseries",
        "transparent": false,
        "transformations": [],
        "options": null,
        "fieldConfig": {
          "defaults": {},
          "overrides": []
        },
        "targets": [
          {
            "expr": "pg_stat_activity_count{service=\"$service\",state=\"active\"}",
            "refId": "A",
            "legendFormat": "{{pg}}"
          }
        ],
        "title": "Active Queries",
        "description": "Number of currently executing queries",
        "gridPos": {
          "h": 9,
          "w": 12,
          "x": 12,
          "y": 30
        },
        "repeatDirection": "h"
      },
      {
        "type": "gauge",
        "transparent": false,
        "transformations": [],
        "options": null,
        "fieldConfig": {
          "defaults": {},
          "overrides": []
        },
        "targets": [
          {
            "expr": "sum(pg_stat_database_blks_hit{service=\"$service\"}) / \n(sum(pg_stat_database_blks_hit{service=\"$service\"}) + sum(pg_stat_database_blks_read{service=\"$service\"})) * 100",
            "refId": "A",
            "legendFormat": "Cache hit %"
          }
        ],
        "title": "Cache Hit Ratio",
        "description": "Buffer cache hit ratio - should be >99% for good performance",
        "gridPos": {
          "h": 9,
          "w": 12,
          "x": 0,
          "y": 39
        },
        "repeatDirection": "h"
      },
      {
        "type": "timeseries",
        "transparent": false,
        "transformations": [],
        "options": null,
        "fieldConfig": {
          "defaults": {},
          "overrides": []
        },
        "targets": [
          {
            "expr": "rate(pg_stat_database_xact_commit{service=\"$service\"}[5m])",
            "refId": "A",
            "legendFormat": "{{datname}} commits/sec"
          },
          {
            "expr": "rate(pg_stat_database_xact_rollback{service=\"$service\"}[5m])",
            "refId": "B",
            "legendFormat": "{{datname}} rollbacks/sec"
          }
        ],
        "title": "Transaction Rate",
        "description": "Transaction commits and rollbacks per second",
        "gridPos": {
          "h": 9,
          "w": 12,
          "x": 12,
          "y": 39
        },
        "repeatDirection": "h"
      },
      {
        "type": "stat",
        "transparent": false,
        "transformations": [],
        "options": null,
        "fieldConfig": {
          "defaults": {},
          "overrides": []
        },
        "targets": [
          {
            "expr": "pg_database_size_bytes{service=\"$service\"}",
            "refId": "A",
            "legendFormat": "{{pg}}"
          }
        ],
        "title": "Database Size",
        "description": "Total database size",
        "gridPos": {
          "h": 9,
          "w": 12,
          "x": 0,
          "y": 48
        },
        "repeatDirection": "h"
      },
      {
        "type": "timeseries",
        "transparent": false,
        "transformations": [],
        "options": null,
        "fieldConfig": {
          "defaults": {},
          "overrides": []
        },
        "targets": [
          {
            "expr": "histogram_quantile(0.95, sum by (le) (rate(pg_stat_statements_mean_exec_time_seconds_bucket{service=\"$service\"}[5m])))",
            "refId": "A",
            "legendFormat": "{{pg}}"
          }
        ],
        "title": "Query Duration (p95)",
        "description": "Query execution time (95th percentile)",
        "gridPos": {
          "h": 9,
          "w": 12,
          "x": 12,
          "y": 48
        },
        "repeatDirection": "h"
      },
      {
        "type": "timeseries",
        "transparent": false,
        "transformations": [],
        "options": null,
        "fieldConfig": {
          "defaults": {},
          "overrides": []
        },
        "targets": [
          {
            "expr": "rate(pg_stat_database_deadlocks{service=\"$service\"}[5m])",
            "refId": "A",
            "legendFormat": "{{pg}}"
          }
        ],
        "title": "Deadlocks",
        "description": "Deadlocks per second - should be near zero",
        "gridPos": {
          "h": 9,
          "w": 12,
          "x": 0,
          "y": 57
        },
        "repeatDirection": "h"
      },
      {
        "type": "timeseries",
        "transparent": false,
        "transformations": [],
        "options": null,
        "fieldConfig": {
          "defaults": {},
          "overrides": []
        },
        "targets": [
          {
            "expr": "pg_replication_lag_seconds{service=\"$service\"}",
            "refId": "A",
            "legendFormat": "{{pg}}"
          }
        ],
        "title": "Replication Lag",
        "description": "Replication lag in seconds",
        "gridPos": {
          "h": 9,
          "w": 12,
          "x": 12,
          "y": 57
        },
        "repeatDirection": "h"
      },
      {
        "type": "timeseries",
        "transparent": false,
        "transformations": [],
        "options": null,
        "fieldConfig": {
          "defaults": {},
          "overrides": []
        },
        "targets": [
          {
            "expr": "sum(pg_stat_user_tables_n_dead_tup{service=\"$service\"}) by (relname)",
            "refId": "A",
            "legendFormat": "{{pg}}"
          }
        ],
        "title": "Table Bloat (Dead Tuples)",
        "description": "Dead tuples indicating table bloat - vacuum if high",
        "gridPos": {
          "h": 9,
          "w": 12,
          "x": 0,
          "y": 66
        },
        "repeatDirection": "h"
      },
      {
        "type": "gauge",
        "transparent": false,
        "transformations": [],
        "options": null,
        "fieldConfig": {
          "defaults": {},
          "overrides": []
        },
        "targets": [
          {
            "expr": "pg_stat_database_numbackends{service=\"$service\"} / \non() group_left pg_settings_max_connections{service=\"$service\"} * 100",
            "refId": "A",
            "legendFormat": "Pool usage %"
          }
        ],
        "title": "Connection Pool Utilization",
        "description": "Connection pool utilization percentage",
        "gridPos": {
          "h": 9,
          "w": 12,
          "x": 12,
          "y": 66
        },
        "repeatDirection": "h"
      },
      {
        "type": "timeseries",
        "transparent": false,
        "transformations": [],
        "options": null,
        "fieldConfig": {
          "defaults": {},
          "overrides": []
        },
        "targets": [
          {
            "expr": "redis_memory_used_bytes{service=\"$service\"}",
            "refId": "A",
            "legendFormat": "{{redis}}"
          }
        ],
        "title": "Redis Memory Usage",
        "description": "Redis memory consumption",
        "gridPos": {
          "h": 9,
          "w": 12,
          "x": 0,
          "y": 75
        },
        "repeatDirection": "h"
      },
      {
        "type": "gauge",
        "transparent": false,
        "transformations": [],
        "options": null,
        "fieldConfig": {
          "defaults": {},
          "overrides": []
        },
        "targets": [
          {
            "expr": "sum(rate(cache_hits_total{service=\"$service\"}[5m])) / \n(sum(rate(cache_hits_total{service=\"$service\"}[5m])) + \nsum(rate(cache_misses_total{service=\"$service\"}[5m]))) * 100",
            "refId": "A",
            "legendFormat": "Hit rate %"
          }
        ],
        "title": "Cache Hit Rate",
        "description": "Cache hit rate - should be >90% for good performance",
        "gridPos": {
          "h": 9,
          "w": 12,
          "x": 12,
          "y": 75
        },
        "repeatDirection": "h"
      },
      {
        "type": "timeseries",
        "transparent": false,
        "transformations": [],
        "options": null,
        "fieldConfig": {
          "defaults": {},
          "overrides": []
        },
        "targets": [
          {
            "expr": "redis_connected_clients{service=\"$service\"}",
            "refId": "A",
            "legendFormat": "{{redis}}"
          }
        ],
        "title": "Connected Clients",
        "description": "Number of connected clients",
        "gridPos": {
          "h": 9,
          "w": 12,
          "x": 0,
          "y": 84
        },
        "repeatDirection": "h"
      },
      {
        "type": "timeseries",
        "transparent": false,
        "transformations": [],
        "options": null,
        "fieldConfig": {
          "defaults": {},
          "overrides": []
        },
        "targets": [
          {
            "expr": "rate(cache_hits_total{service=\"$service\"}[5m])",
            "refId": "A",
            "legendFormat": "Hits/sec"
          },
          {
            "expr": "rate(cache_misses_total{service=\"$service\"}[5m])",
            "refId": "B",
            "legendFormat": "Misses/sec"
          }
        ],
        "title": "Cache Hits vs Misses",
        "description": "Cache hits and misses per second",
        "gridPos": {
          "h": 9,
          "w": 12,
          "x": 12,
          "y": 84
        },
        "repeatDirection": "h"
      },
      {
        "type": "timeseries",
        "transparent": false,
        "transformations": [],
        "options": null,
        "fieldConfig": {
          "defaults": {},
          "overrides": []
        },
        "targets": [
          {
            "expr": "rate(redis_evicted_keys_total{service=\"$service\"}[5m])",
            "refId": "A",
            "legendFormat": "{{redis}}"
          }
        ],
        "title": "Evicted Keys",
        "description": "Keys evicted due to memory pressure - should be zero",
        "gridPos": {
          "h": 9,
          "w": 12,
          "x": 0,
          "y": 93
        },
        "repeatDirection": "h"
      },
      {
        "type": "timeseries",
        "transparent": false,
        "transformations": [],
        "options": null,
        "fieldConfig": {
          "defaults": {},
          "overrides": []
        },
        "targets": [
          {
            "expr": "rate(redis_expired_keys_total{service=\"$service\"}[5m])",
            "refId": "A",
            "legendFormat": "{{redis}}"
          }
        ],
        "title": "Expired Keys",
        "description": "Keys expired per second due to TTL",
        "gridPos": {
          "h": 9,
          "w": 12,
          "x": 12,
          "y": 93
        },
        "repeatDirection": "h"
      },
      {
        "type": "timeseries",
        "transparent": false,
        "transformations": [],
        "options": null,
        "fieldConfig": {
          "defaults": {},
          "overrides": []
        },
        "targets": [
          {
            "expr": "rate(redis_commands_processed_total{service=\"$service\"}[5m])",
            "refId": "A",
            "legendFormat": "{{redis}}"
          }
        ],
        "title": "Commands/sec",
        "description": "Redis commands processed per second",
        "gridPos": {
          "h": 9,
          "w": 12,
          "x": 0,
          "y": 102
        },
        "repeatDirection": "h"
      },
      {
        "type": "stat",
        "transparent": false,
        "transformations": [],
        "options": null,
        "fieldConfig": {
          "defaults": {},
          "overrides": []
        },
        "targets": [
          {
            "expr": "sum(redis_db_keys{service=\"$service\"})",
            "refId": "A",
            "legendFormat": "{{redis}}"
          }
        ],
        "title": "Total Keys",
        "description": "Total number of keys in database",
        "gridPos": {
          "h": 9,
          "w": 12,
          "x": 12,
          "y": 102
        },
        "repeatDirection": "h"
      }
    ]
  },
  "overwrite": true
}